scrilla/__init__.py
scrilla/cache.py
scrilla/files.py
scrilla/main.py
scrilla/services.py
scrilla/settings.py
scrilla/version.txt
scrilla/analysis/__init__.py
scrilla/analysis/estimators.py
scrilla/analysis/integration.py
scrilla/analysis/markets.py
scrilla/analysis/optimizer.py
scrilla/analysis/plotter.py
scrilla/analysis/models/__init__.py
scrilla/analysis/models/geometric/__init__.py
scrilla/analysis/models/geometric/probability.py
scrilla/analysis/models/geometric/statistics.py
scrilla/analysis/models/reversion/__init__.py
scrilla/analysis/models/reversion/probability.py
scrilla/analysis/models/reversion/statistics.py
scrilla/analysis/objects/__init__.py
scrilla/analysis/objects/cashflow.py
scrilla/analysis/objects/portfolio.py
scrilla/cloud/__init__.py
scrilla/cloud/aws.py
scrilla/data/assets/arrow-back-circle-outline.svg
scrilla/data/assets/arrow-back-circle-sharp.svg
scrilla/data/assets/calculator-outline.svg
scrilla/data/assets/calculator-sharp.svg
scrilla/data/assets/calendar-number-outline.svg
scrilla/data/assets/calendar-number-sharp.svg
scrilla/data/assets/calendar-outline.svg
scrilla/data/assets/calendar-sharp.svg
scrilla/data/assets/card-outline.svg
scrilla/data/assets/card-sharp.svg
scrilla/data/assets/cash-outline.svg
scrilla/data/assets/cash-sharp.svg
scrilla/data/assets/close-circle-outline.svg
scrilla/data/assets/close-circle-sharp.svg
scrilla/data/assets/document-text-outline.svg
scrilla/data/assets/document-text-sharp.svg
scrilla/data/assets/download-outline.svg
scrilla/data/assets/download-sharp.svg
scrilla/data/assets/help-circle-outline.svg
scrilla/data/assets/help-circle-sharp.svg
scrilla/data/assets/information-circle-outline.svg
scrilla/data/assets/information-circle-sharp.svg
scrilla/data/assets/logo-github.svg
scrilla/data/assets/logo-python.svg
scrilla/data/assets/okay-sharp.svg
scrilla/data/assets/okay.svg
scrilla/data/assets/trash-outline.svg
scrilla/data/assets/trash-sharp.svg
scrilla/data/cache/.gitkeep
scrilla-1.6.0.dist-info/LICENSE
scrilla-1.6.0.dist-info/METADATA
scrilla-1.6.0.dist-info/WHEEL
scrilla-1.6.0.dist-info/entry_points.txt
scrilla-1.6.0.dist-info/top_level.txt
scrilla-1.6.0.dist-info/RECORD
