Metadata-Version: 2.1
Name: scrilla
Version: 1.6.0
Summary: a financial optimization program
Author: Grant Moore
Author-email: chinchalinchin@gmail.com
License: GNU GPL v3
Project-URL: Documentation, https://chinchalinchin.github.io/scrilla/
Project-URL: Source, https://github.com/chinchalinchin/scrilla
Keywords: finance,statistics,stock market,equities,cryptocurrencies,optimization
Platform: any
Requires-Python: >=3.8
License-File: LICENSE
Requires-Dist: boto3 (>=1.24.13)
Requires-Dist: numpy (>=1.19.3)
Requires-Dist: scipy (>=1.5.4)
Requires-Dist: matplotlib (>=3.3.3)
Requires-Dist: holidays (>=0.14.2)
Requires-Dist: python-dateutil (>=2.8.2)
Requires-Dist: python-dotenv (>=0.15.0)
Requires-Dist: requests (>=2.25.0)
Requires-Dist: defusedxml (>=0.7.1)
Requires-Dist: PySide2 (>=5.15.2.1)
Provides-Extra: gui
Requires-Dist: PySide6 (>=6.2.0) ; extra == 'gui'
